pyjawk/__init__.py
pyjawk/__main__.py
pyjawk/_meta.py
pyjawk/attrdict.py
pyjawk/color.py
pyjawk/license.py
pyjawk/yaml.py
pyjawk-1.2.0.dist-info/DESCRIPTION.rst
pyjawk-1.2.0.dist-info/METADATA
pyjawk-1.2.0.dist-info/RECORD
pyjawk-1.2.0.dist-info/WHEEL
pyjawk-1.2.0.dist-info/entry_points.txt
pyjawk-1.2.0.dist-info/metadata.json
pyjawk-1.2.0.dist-info/top_level.txt
