Metadata-Version: 2.0
Name: pyjawk
Version: 1.2.0
Summary: A Python-based stream editor for json documents
Home-page: https://gitlab.com/Taywee/pyjawk
Author: Taylor C. Richberger
License: MIT
Keywords: utility
Platform: UNKNOWN
Classifier: Development Status :: 5 - Production/Stable
Classifier: Programming Language :: Python :: 3
Classifier: Programming Language :: Python :: 3.6
Classifier: Operating System :: OS Independent
Classifier: License :: OSI Approved :: MIT License
Classifier: License :: OSI Approved :: MIT License
Classifier: Topic :: Utilities
Requires-Dist: appdirs
Requires-Dist: msgpack
Requires-Dist: packaging
Requires-Dist: ptpython
Requires-Dist: pygments
Requires-Dist: ruamel.yaml
